environs_serviceurl/__init__.py
environs_serviceurl/parser.py
environs_serviceurl-1.0.1.dist-info/DESCRIPTION.rst
environs_serviceurl-1.0.1.dist-info/METADATA
environs_serviceurl-1.0.1.dist-info/RECORD
environs_serviceurl-1.0.1.dist-info/WHEEL
environs_serviceurl-1.0.1.dist-info/metadata.json
environs_serviceurl-1.0.1.dist-info/top_level.txt
