Metadata-Version: 2.0
Name: environs-serviceurl
Version: 1.0.1
Summary: Add service URL parsing support for environs
Home-page: http://github.com/flowroute/environs-serviceurl
Author: Dan Root
Author-email: rootdan+pypi@gmail.com
License: MIT
Platform: any
Classifier: Development Status :: 3 - Alpha
Classifier: Intended Audience :: Developers
Classifier: License :: OSI Approved :: MIT License
Classifier: Operating System :: OS Independent
Classifier: Programming Language :: Python
Classifier: Programming Language :: Python :: 2.7
Classifier: Programming Language :: Python :: 3.3
Classifier: Programming Language :: Python :: 3.4
Classifier: Programming Language :: Python :: 3.5
Requires-Dist: environs
Provides-Extra: all
Requires-Dist: environs; extra == 'all'
Requires-Dist: pytest; extra == 'all'
Requires-Dist: pytest-cov; extra == 'all'
Requires-Dist: pytest-flake8; extra == 'all'
Provides-Extra: install
Requires-Dist: environs; extra == 'install'
Provides-Extra: setup
Provides-Extra: tests
Requires-Dist: pytest; extra == 'tests'
Requires-Dist: pytest-cov; extra == 'tests'
Requires-Dist: pytest-flake8; extra == 'tests'
